botpie/__init__.py
botpie/bot.py
botpie/cmd.py
botpie/exception.py
botpie/utils.py
botpie-0.0.1.dist-info/LICENSE
botpie-0.0.1.dist-info/METADATA
botpie-0.0.1.dist-info/WHEEL
botpie-0.0.1.dist-info/top_level.txt
botpie-0.0.1.dist-info/RECORD
