Metadata-Version: 2.1
Name: botpie
Version: 0.0.1
Summary: A Python framework for managing chatbots
Home-page: https://github.com/gwilkes/botpie
Author: gwilkes
License: MIT
Platform: UNKNOWN
Classifier: Programming Language :: Python :: 3
Classifier: License :: OSI Approved :: MIT License
Classifier: Operating System :: OS Independent
